{
    "snippet": {
        "3960000": {
            "timestamp": 1328123863.227807, 
            "secret": "OMpEmreaktJxUSHR"
        }, 
        "2760000": {
            "timestamp": 1328124015.301524, 
            "secret": "crIhgrTjCYyymQtc"
        }, 
        "2730000": {
            "timestamp": 1328124015.301524, 
            "secret": "YNYygUzYWqYORGDS"
        }
    }, 
    "review": {
        "2730000": {
            "timestamp": 1328124015.301524, 
            "secret": "utljEVGhlpvEZADX"
        }
    }
}